kse801/__init__.py
kse801/_util.py
kse801/abc/__init__.py
kse801/abc/_load.py
kse801/crowdsignal/__init__.py
kse801/crowdsignal/_load.py
kse801/kaist/__init__.py
kse801/kaist/_load.py
kse801/res/abc/activity.pkl.gz
kse801/res/abc/app_usage.pkl.gz
kse801/res/abc/location.pkl.gz
kse801/res/abc/plugged.pkl.gz
kse801/res/abc/receptivity.pkl.gz
kse801/res/abc/ringer_mode.pkl.gz
kse801/res/abc/screen.pkl.gz
kse801/res/crowdsignal/accelerometer_phone.pkl.gz
kse801/res/crowdsignal/accelerometer_smartwatch.pkl.gz
kse801/res/crowdsignal/battery_phone.pkl.gz
kse801/res/crowdsignal/battery_smartwatch.pkl.gz
kse801/res/crowdsignal/bluetooth_phone.pkl.gz
kse801/res/crowdsignal/connectivity_phone.pkl.gz
kse801/res/crowdsignal/gsm_phone.pkl.gz
kse801/res/crowdsignal/gyroscope_phone.pkl.gz
kse801/res/crowdsignal/gyroscope_smartwatch.pkl.gz
kse801/res/crowdsignal/heart_rate_smartwatch.pkl.gz
kse801/res/crowdsignal/labels.pkl.gz
kse801/res/crowdsignal/light_phone.pkl.gz
kse801/res/crowdsignal/location_phone.pkl.gz
kse801/res/crowdsignal/magnetometer_phone.pkl.gz
kse801/res/crowdsignal/magnetometer_smartwatch.pkl.gz
kse801/res/crowdsignal/pressure_phone.pkl.gz
kse801/res/crowdsignal/proximity_phone.pkl.gz
kse801/res/crowdsignal/screen_phone.pkl.gz
kse801/res/crowdsignal/sms_phone.pkl.gz
kse801/res/crowdsignal/wlan_phone.pkl.gz
kse801/res/kaist/accelerometer.pkl.gz
kse801/res/kaist/activity_event.pkl.gz
kse801/res/kaist/app_usage.pkl.gz
kse801/res/kaist/data_traffic.pkl.gz
kse801/res/kaist/gsr.pkl.gz
kse801/res/kaist/heart_rate.pkl.gz
kse801/res/kaist/location.pkl.gz
kse801/res/kaist/rr_interval.pkl.gz
kse801/res/kaist/skin_temperature.pkl.gz
kse801_dataset-0.1.2.dist-info/METADATA
kse801_dataset-0.1.2.dist-info/WHEEL
kse801_dataset-0.1.2.dist-info/top_level.txt
kse801_dataset-0.1.2.dist-info/RECORD
