Metadata-Version: 2.1
Name: kse801-dataset
Version: 0.1.2
Summary: UNKNOWN
Home-page: UNKNOWN
Author: Woohyeok Choi
Author-email: woohyeok.choi@kaist.ac.kr
License: UNKNOWN
Platform: UNKNOWN
Classifier: Programming Language :: Python :: 3
Classifier: Topic :: Scientific/Engineering
Requires-Python: >=3.6
Requires-Dist: pandas
